pegtree/__init__.py
pegtree/cj.py
pegtree/colab.py
pegtree/graph.py
pegtree/loader.py
pegtree/loader2.py
pegtree/main.py
pegtree/nez.py
pegtree/nezcc.py
pegtree/optimizer.py
pegtree/pasm.py
pegtree/pasm2.py
pegtree/peg.py
pegtree/peg2.py
pegtree/terminal.py
pegtree/tpeg_pasm.py
pegtree/tree.py
pegtree/treeconv.py
pegtree/visitor.py
pegtree/cjdic/VB5.txt
pegtree/cjdic/VG5.txt
pegtree/cjdic/VK5.txt
pegtree/cjdic/VM5.txt
pegtree/cjdic/VR5.txt
pegtree/cjdic/VS5.txt
pegtree/cjdic/VT5.txt
pegtree/cjdic/VW5.txt
pegtree/code/ts.txt
pegtree/grammar/a.tpeg
pegtree/grammar/chibi.pegtree
pegtree/grammar/chibi.tpeg
pegtree/grammar/cj.tpeg
pegtree/grammar/cj0.tpeg
pegtree/grammar/csv.tpeg
pegtree/grammar/email.tpeg
pegtree/grammar/es4.tpeg
pegtree/grammar/java8.tpeg
pegtree/grammar/json.tpeg
pegtree/grammar/kotonoha.pegtree
pegtree/grammar/math-infix.tpeg
pegtree/grammar/math.pegtree
pegtree/grammar/math.tpeg
pegtree/grammar/pegtree.tpeg
pegtree/grammar/puppy.tpeg
pegtree/grammar/tpeg.tpeg
pegtree/grammar/types.tpeg
pegtree/grammar/utf8.tpeg
pegtree/grammar/xml.tpeg
pegtree/grammar/cjdic/ADJ.txt
pegtree/grammar/cjdic/ADWORD.txt
pegtree/grammar/cjdic/CONJ.txt
pegtree/grammar/cjdic/NONUNIT.txt
pegtree/grammar/cjdic/NOUN.txt
pegtree/grammar/cjdic/UNIT.txt
pegtree/grammar/cjdic/VERB1.txt
pegtree/grammar/cjdic/VERB5BA.txt
pegtree/grammar/cjdic/VERB5GA.txt
pegtree/grammar/cjdic/VERB5KA.txt
pegtree/grammar/cjdic/VERB5MA.txt
pegtree/grammar/cjdic/VERB5NA.txt
pegtree/grammar/cjdic/VERB5RA.txt
pegtree/grammar/cjdic/VERB5SA.txt
pegtree/grammar/cjdic/VERB5TA.txt
pegtree/grammar/cjdic/VERB5WA.txt
pegtree-0.9.16.dist-info/LICENSE
pegtree-0.9.16.dist-info/METADATA
pegtree-0.9.16.dist-info/WHEEL
pegtree-0.9.16.dist-info/entry_points.txt
pegtree-0.9.16.dist-info/top_level.txt
pegtree-0.9.16.dist-info/RECORD
